AUTHORS.rst
CONTRIBUTING.rst
HISTORY.rst
LICENSE
MANIFEST.in
README.md
setup.cfg
setup.py
acl_stats/__init__.py
acl_stats/acl_stats.py
acl_stats/cli.py
acl_stats.egg-info/PKG-INFO
acl_stats.egg-info/SOURCES.txt
acl_stats.egg-info/dependency_links.txt
acl_stats.egg-info/entry_points.txt
acl_stats.egg-info/not-zip-safe
acl_stats.egg-info/requires.txt
acl_stats.egg-info/top_level.txt
docs/Makefile
docs/authors.rst
docs/conf.py
docs/contributing.rst
docs/history.rst
docs/index.rst
docs/installation.rst
docs/make.bat
docs/readme.rst
docs/usage.rst
tests/test_acl_stats.py