Metadata-Version: 1.1
Name: acl-stats
Version: 0.1.3
Summary: Quickly gather access-lists stats from Cisco ASA Firewalls
Home-page: https://github.com/diogoandre/acl_stats
Author: Diogo André de Assumpção
Author-email: diogo.aa@protonmail.com
License: MIT license
Keywords: acl_stats
Platform: UNKNOWN
Classifier: Development Status :: 2 - Pre-Alpha
Classifier: Intended Audience :: Developers
Classifier: License :: OSI Approved :: MIT License
Classifier: Natural Language :: English
Classifier: Programming Language :: Python :: 3
Classifier: Programming Language :: Python :: 3.4
Classifier: Programming Language :: Python :: 3.5
Classifier: Programming Language :: Python :: 3.6
Classifier: Programming Language :: Python :: 3.7
